chargedPlanner/LuccaAPI.py
chargedPlanner/__init__.py
chargedPlanner/chargedPlanner.py
chargedPlanner/create_config.py
chargedPlanner/decorators.py
chargedPlanner/tools.py
chargedPlanner/data/Project.json
chargedPlanner/data/config.json
chargedplanner-0.5.4.dist-info/licenses/LICENSE
chargedplanner-0.5.4.dist-info/METADATA
chargedplanner-0.5.4.dist-info/WHEEL
chargedplanner-0.5.4.dist-info/top_level.txt
chargedplanner-0.5.4.dist-info/RECORD
