Metadata-Version: 2.4
Name: chargedPlanner
Version: 0.5.4
Summary: A tool allowing to planify the work of developers
Author-email: Daniele TRIMARCHI <daniele.trimarchi@iconeus.com>
Classifier: Programming Language :: Python :: 3
Classifier: License :: OSI Approved :: MIT License
Classifier: Operating System :: OS Independent
Requires-Python: >=3.6
License-File: LICENSE
Requires-Dist: colorama==0.4.6
Requires-Dist: flake8==7.2.0
Requires-Dist: freezegun==1.5.1
Requires-Dist: holidays==0.71
Requires-Dist: keyring==25.6.0
Requires-Dist: numpy==2.2.4
Requires-Dist: pandas==2.2.3
Requires-Dist: plotly==6.0.1
Requires-Dist: ratelimit==2.2.1
Requires-Dist: requests==2.32.3
Dynamic: license-file
